customTraceback/__init__.py
customTraceback/customTraceback.py
tracebackSilencer/__init__.py
tracebackSilencer/tracebackSilencer.py
tracebacklib-0.1.0.dist-info/METADATA
tracebacklib-0.1.0.dist-info/WHEEL
tracebacklib-0.1.0.dist-info/top_level.txt
tracebacklib-0.1.0.dist-info/RECORD
