Metadata-Version: 2.4
Name: tracebackLib
Version: 0.1.0
Summary: Traceback silencer and custom traceback tools
Author-email: Avtho <Th3ou1d3x@example.com>
License: MIT
Requires-Python: >=3.8
Requires-Dist: AnsiCoolFORMATING
